nombre_en_lettres_mg/__init__.py
nombre_en_lettres_mg/nombre_en_lettres.py
nombre_en_lettres_mg-0.1.dist-info/LICENSE
nombre_en_lettres_mg-0.1.dist-info/METADATA
nombre_en_lettres_mg-0.1.dist-info/WHEEL
nombre_en_lettres_mg-0.1.dist-info/top_level.txt
nombre_en_lettres_mg-0.1.dist-info/RECORD
