Metadata-Version: 2.2
Name: nombre_en_lettres_mg
Version: 0.1
Summary: Une bibliothèque pour convertir les nombres en lettres en malagasy.
Home-page: https://github.com/Daylamiy06
Author: Day Lamy
Author-email: hatsudai1@gmail.com
License: Propriétaire
Classifier: Programming Language :: Python :: 3
Classifier: License :: Other/Proprietary License
Classifier: Operating System :: OS Independent
Requires-Python: >=3.6
License-File: LICENSE
Dynamic: author
Dynamic: author-email
Dynamic: classifier
Dynamic: description
Dynamic: description-content-type
Dynamic: home-page
Dynamic: license
Dynamic: requires-python
Dynamic: summary
